logger/LDMLogger.py
logger/__init__.py
ldm_python_client_lib-0.0.8.dist-info/LICENSE.txt
ldm_python_client_lib-0.0.8.dist-info/METADATA
ldm_python_client_lib-0.0.8.dist-info/WHEEL
ldm_python_client_lib-0.0.8.dist-info/top_level.txt
ldm_python_client_lib-0.0.8.dist-info/RECORD
