Metadata-Version: 2.1
Name: ldm-python-client-lib
Version: 0.0.8
Summary: Python client side functions for working with LDM framework.
Home-page: https://github.com/IMCS-DL4media/LDM_midterm
Author: sergejsrk
Author-email: rikachovs@gmail.com
License: MIT
Download-URL: https://pypi.org/project/ldm_python_client_lib/
Keywords: LDM,Python 3,ML life cycle
Platform: UNKNOWN
Requires-Dist: requests
